amz_widgets/__init__.py
amz_widgets/form_entry.py
amz_widgets-0.0.2.dist-info/METADATA
amz_widgets-0.0.2.dist-info/WHEEL
amz_widgets-0.0.2.dist-info/licenses/LICENSE.txt
amz_widgets-0.0.2.dist-info/RECORD
