Metadata-Version: 2.1
Name: amz_widgets
Version: 0.0.2
Summary: Collection of useful tkinter widgets
Project-URL: Homepage, https://github.com/dmalves/amz_widgets
Project-URL: Bug Tracker, https://github.com/dmalves/amz_widgets/issues
Author-email: Daniel de Matos Alves <dmalves.programmer@outlook.com>
License-File: LICENSE.txt
Classifier: License :: OSI Approved :: MIT License
Classifier: Operating System :: OS Independent
Classifier: Programming Language :: Python :: 3
Requires-Python: >=3.10
Requires-Dist: ttkbootstrap>=1.10.1
